LICENSE
README.md
setup.cfg
setup.py
passholder/__init__.py
passholder/account.py
passholder/controller.py
passholder/db.py
passholder/errors.py
passholder/terminal_interface.py
passholder.egg-info/PKG-INFO
passholder.egg-info/SOURCES.txt
passholder.egg-info/dependency_links.txt
passholder.egg-info/entry_points.txt
passholder.egg-info/requires.txt
passholder.egg-info/top_level.txt