Metadata-Version: 2.1
Name: passholder
Version: 0.1.4
Summary: Password manager
Home-page: https://github.com/aslanchek/Passholder
License: GPL-3.0
Download-URL: https://github.com/aslanchek/Passholder/archive/refs/tags/v0.1.4-alpha.tar.gz
Platform: UNKNOWN
Classifier: Development Status :: 3 - Alpha
Classifier: Intended Audience :: End Users/Desktop
Classifier: Topic :: Database
Classifier: License :: OSI Approved :: GNU General Public License v3 (GPLv3)
Classifier: Programming Language :: Python :: 3.8
License-File: LICENSE
